<?xml version="1.0" encoding="utf-8" ?>
<Driver xmlns="http://code.google.com/p/open-zwave/" version="3" home_id="0xd3cf129c" node_id="1" api_capabilities="0" controller_capabilities="8" poll_interval="60000" poll_interval_between="false">
	<Node id="1" name="" location="" basic="2" generic="2" specific="1" type="Static PC Controller" listening="true" frequentListening="false" beaming="true" routing="true" max_baud_rate="40000" version="4" query_stage="Complete">
		<Manufacturer id="0109" name="Vision">
			<Product type="1001" id="0105" name="ZU1401 Z-Wave USB Stick" />
		</Manufacturer>
		<CommandClasses>
			<CommandClass id="32" name="COMMAND_CLASS_BASIC" version="1" after_mark="true">
				<Instance index="1" />
				<Value type="byte" genre="basic" instance="1" index="0" label="Basic" units="" read_only="false" write_only="false" verify_changes="false" poll_intensity="0" min="0" max="255" value="0" />
			</CommandClass>
		</CommandClasses>
	</Node>
	<Node id="2" name="" location="" basic="4" generic="16" specific="1" type="Binary Power Switch" listening="true" frequentListening="false" beaming="true" routing="true" max_baud_rate="40000" version="3" query_stage="Probe">
		<Manufacturer id="" name="">
			<Product type="" id="" name="" />
		</Manufacturer>
		<CommandClasses>
			<CommandClass id="32" name="COMMAND_CLASS_BASIC" version="1" mapping="37">
				<Instance index="1" />
			</CommandClass>
			<CommandClass id="37" name="COMMAND_CLASS_SWITCH_BINARY" version="1">
				<Instance index="1" />
				<Value type="bool" genre="user" instance="1" index="0" label="Switch" units="" read_only="false" write_only="false" verify_changes="false" poll_intensity="0" min="0" max="0" value="False" />
			</CommandClass>
			<CommandClass id="39" name="COMMAND_CLASS_SWITCH_ALL" version="1">
				<Instance index="1" />
				<Value type="list" genre="system" instance="1" index="0" label="Switch All" units="" read_only="false" write_only="false" verify_changes="false" poll_intensity="0" min="0" max="0" vindex="0" size="1">
					<Item label="Disabled" value="0" />
					<Item label="Off Enabled" value="1" />
					<Item label="On Enabled" value="2" />
					<Item label="On and Off Enabled" value="255" />
				</Value>
			</CommandClass>
		</CommandClasses>
	</Node>
</Driver>
